Workbook

Sheet Sales 
A1: CashLens - BeanBox Café
A2: AI-Power Cash-Flow Decision Assistant
A3: Customer | C3: Invoice ID | E3: Invoice Date | H3: Amount (Dhs) | I3: Expected Payment | K3: Status
A4: City Office LLC | C4: S00003 | E4: 46266 | H4: 12000 | I4: 46275 | K4: Paid
A5: Green Towers LLC | C5: S00008 | E5: 46268 | H5: 18000 | I5: 46290 | K5: Quotation Pending
A6: TechHub Dubai | C6: S00009 | E6: 46270 | H6: 25000 | I6: 46300 | K6: Quotation Pending
A7: Marina Events Dubai | C7: S00010 | E7: 46273 | H7: 15000 | I7: 46310 | K7: Quotation Pending
A8: Downtown Co. | C8: S00011 | E8: 46275 | H8: 9500 | I8: 46293 | K8: Quotation Pending
A9: BlueSky Media | C9: S00012 | E9: 46277 | H9: 7500 | I9: 46297 | K9: Quotation Pending
A10: JLT Services Dubai | C10: S00013 | E10: 46279 | H10: 11000 | I10: 46295 | K10: Quotation Pending
A11: Palm Group | C11: S00014 | E11: 46280 | H11: 16000 | I11: 46366 | K11: Quotation Pending
A12: Metro Offices | C12: S00015 | E12: 46281 | H12: 8500 | I12: 25/09/2026 | K12: Sales Order Confirmed
A13: Creek Consulting | C13: S00016 | E13: 46282 | H13: 14000 | I13: 20/10/2026 | K13: Sales Order Confirmed
A14: Gulf Design | C14: S00017 | E14: 46283 | H14: 10000 | I14: 46152 | K14: Sales Order Confirmed
A15: Horizon Trading | C15: INV012 | E15: 46284 | H15: 13500 | I15: 15/10/2026 | K15: Sales Order Confirmed
A16: Summary
A17: Total Sales | C17: =SUM(H4:H15) -> 160000
A18: Payments Received | C18: =$H$4 -> 12000
A19: Oustanding Receivables | C19: =SUM(H5:H15) -> 148000

Sheet Purchases
A1: CashLens - BeanBox Café
A2: AI-Power Cash-Flow Decision Assistant
A3: Supplier | C3: Bill ID | E3: Bill Date | H3: Amount (Dhs) | I3: Due Date | K3: Status
A4: Emirates Coffee Roasters | C4: BILL001 | E4: 46062 | H4: 8000 | I4: 46283 | K4: Pending
A5: FreshFoods UAE | C5: BILL002 | E5: 46121 | H5: 6500 | I5: 22/09/26 | K5: Pending
A6: Gulf Equipments | C6: BILL003 | E6: 46212 | H6: 12000 | I6: 30/09/26 | K6: Pending
A7: PackRight UAE | C7: BILL004 | E7: 46304 | H7: 4000 | I7: 46300 | K7: Pending
A8: Dairy Fresh UAE | C8: BILL005 | E8: 46335 | H8: 5500 | I8: 46290 | K8: Pending
A9: Al Noor Bakery | C9: BILL006 | E9: 46365 | H9: 3500 | I9: 46293 | K9: Pending
A10: Dubai Beverage Co. | C10: BILL007 | E10: 46279 | H10: 7000 | I10: 46297 | K10: Pending
A11: Clean Pro Services | C11: BILL008 | E11: 46280 | H11: 2800 | I11: 30/09/26 | K11: Pending
A12: CoffeeTech Solutions | C12: BILL009 | E12: 46281 | H12: 9000 | I12: 46305 | K12: Pending
A13: FreshFoods UAE | C13: BILL010 | E13: 46282 | H13: 6000 | I13: 15/10/26 | K13: Pending
A14: PackRight UAE | C14: BILL011 | E14: 46283 | H14: 3200 | I14: 46152 | K14: Pending
A15: =$A$4 -> Emirates Coffee Roasters | C15: BILL012 | E15: 46284 | H15: 7500 | I15: 20/10/26 | K15: Pending
A16: Summary
A17: Total Purchases | C17: =SUM(H4:H15) -> 75000

Sheet Expenses 
A1: CashLens - BeanBox Café
A2: AI-Power Cash-Flow Decision Assistant
A3: Expenses | C3: Amount (Dhs) | E3: Date | H3: Due Date | I3: Status
A4: Rent | C4: 15000 | E4: 46031 | H4: 46032 | I4: Pending
A5: Salaries | C5: 20000 | E5: 46031 | H5: 30/09/26 | I5: Pending
A6: Electricity | C6: 3000 | E6: 46151 | H6: 25/09/26 | I6: Pending
A7: Water | C7: 1200 | E7: 46151 | H7: 25/09/26 | I7: Pending
A8: Internet | C8: 800 | E8: 46182 | H8: 20/09/26 | I8: Pending
A9: Marketing | C9: 2500 | E9: 46243 | H9: 20/09/26 | I9: Paid
A10: Insurance | C10: 4000 | E10: 46304 | H10: 30/09/26 | I10: Pending
A11: Maintenance | C11: 2000 | E11: 46365 | H11: 28/09/26 | I11: Pending
A12: Staff Transport | C12: 1500 | E12: 14/09/26 | H12: 30/09/26 | I12: Pending
A13: Software Subscriptions | C13: 1000 | E13: 15/09/26 | H13: 30/09/26 | I13: Pending
A15: Total Amount | C15: =SUM(C4:D13) -> 51000

Sheet Cash
A1: CashLens - BeanBox Café
A2: AI-Power Cash-Flow Decision Assistant
A3: Date | C3: Opening Cash (Dhs) | E3: Cash In (Dhs) | H3: Cash Out (Dhs) | K3: Closing Cash (Dhs)
A4: 19/09/2026 | C4: 50000 | E4: 0 | H4: 0 | K4: =C4+E4-H4 -> 50000

Sheet Forecast
A1: CashLens - BeanBox Café
A2: AI-Power Cash-Flow Decision Assistant
A3: Cash In Date | C3: Sales Cash In | E3: Purchases Date | G3: Purchases Cash Out | J3: Expenses Date | L3: Expenses Cash Out | O3: Expense Status | Q3: Total Cash Out | T3: Net Cash Flow | W3: Projected Closing Cash | Z3: Actual Cash Balance
A4: 46031 | C4: ='Sales '!H4 -> 12000 | E4: N/A | G4: 0 | J4: N/A | L4: 0 | O4: N/A | Q4: N/A | T4: 12000 | W4: 12000 | Z4: =C4-G5-L5 -> 1500
A5: N/A | C5: 0 | E5: 18/09/26 | G5: 8000 | J5: 46243 | L5: 2500 | O5: Paid | Q5: =SUM(G5,L5) -> 10500 | T5: =C5-Q5 -> -10500 | W5: 1500 | Z5: n/a
A6: N/A | C6: 0 | E6: =Purchases!I5 -> 22/09/26 | G6: 6500 | J6: 46032 | L6: 15000 | O6: Pending | Q6: =SUM(G6,L6) -> 21500 | T6: =C6-Q6 -> -21500 | W6: -20000 | Z6: n/a
A7: N/A | C7: 0 | E7: =Purchases!I6 -> 30/09/26 | G7: 12000 | J7: 30/9/2026 | L7: 20000 | O7: Pending | Q7: =SUM(G7,L7) -> 32000 | T7: =C7-Q7 -> -32000 | W7: -52000 | Z7: n/a
A8: N/A | C8: 0 | E8: 46152 | G8: 4000 | J8: 25/9/26 | L8: 3000 | O8: Pending | Q8: =SUM(G8,L8) -> 7000 | T8: =C8-Q8 -> -7000 | W8: -59000 | Z8: n/a
A9: N/A | C9: 0 | E9: =Purchases!I8 -> 46290 | G9: 5500 | J9: 25/9/26 | L9: 1200 | O9: Pending | Q9: =SUM(G9,L9) -> 6700 | T9: -6700 | W9: =SUM(W8,T9) -> -65700 | Z9: n/a
A10: N/A | C10: 0 | E10: =Purchases!I9 -> 46293 | G10: 3500 | J10: 20/9/26 | L10: 800 | O10: Pending | Q10: =SUM(G10,L10) -> 4300 | T10: -4300 | W10: =SUM(W9,T10) -> -70000 | Z10: n/a
A11: N/A | C11: 0 | E11: =Purchases!I10 -> 46297 | G11: 7000 | J11: 30/9/26 | L11: 4000 | O11: Pending | Q11: =SUM(G11,L11) -> 11000 | T11: -11000 | W11: =SUM(W10,T11) -> -81000 | Z11: n/a
A12: N/A | C12: 0 | E12: =Purchases!I11 -> 30/09/26 | G12: 2800 | J12: 28/9/26 | L12: 2000 | O12: Pending | Q12: =SUM(G12,L12) -> 4800 | T12: -4800 | W12: =SUM(W11,T12) -> -85800 | Z12: n/a
A13: N/A | C13: 0 | E13: =Purchases!I12 -> 46305 | G13: 9000 | J13: 30/9/26 | L13: 1500 | O13: Pending | Q13: =SUM(G13,L13) -> 10500 | T13: -10500 | W13: =SUM(W12,T13) -> -96300 | Z13: n/a
A14: N/A | C14: 0 | E14: =Purchases!I13 -> 15/10/26 | G14: 6000 | J14: 30/9/26 | L14: 1000 | O14: Pending | Q14: =SUM(G14,L14) -> 7000 | T14: -7000 | W14: =SUM(W13,T14) -> -103300 | Z14: n/a
A15: N/A | C15: 0 | E15: 46152 | G15: 3200 | J15: N/A | L15: 0 | O15: n/a | Q15: =SUM(G15,L15) -> 3200 | T15: -3200 | W15: =SUM(W14,T15) -> -106500 | Z15: n/a
A16: N/A | C16: 0 | E16: 20/10/26 | G16: 7500 | J16: N/A | L16: 0 | O16: n/a | Q16: =SUM(G16,L16) -> 7500 | T16: =--7500 -> 7500 | W16: =SUM(W15,T16) -> -99000 | Z16: n/a

Sheet Intelligence 
A1: Date | B1: Projected Cash (Dhs) | D1: Minimum Cash Threshold (Dhs) | G1: Risk Level | J1: Cash in hand | M1: Cash Out | P1: Reason
A2: 46031 | B2: 12000 | D2: 20000 | G2: Warning | J2: 50000 | M2: N/A | P2: Low Sales Cash - In, Smaller Expenses
A3: 46151 | B3: 1500 | D3: 20000 | G3: Warning | J3: 50000 | M3: 10500 | P3: Low Yet Manageable Cash Inflow
A4: 46304 | B4: -20000 | D4: 20000 | G4: Critical | J4: 50000 | M4: 21500 | P4: Expenses Exceed Income Significantly
A5: 15/09/26 | B5: -52000 | D5: 20000 | G5: Critical | J5: 50000 | M5: 32000 | P5: Rent+Salaries + Supplier Dues
A6: 20/092026 | B6: -59000 | D6: 20000 | G6: Critical | J6: 50000 | M6: 7000 | P6: Multiple supplier payments
A7: 25/09/26 | B7: -65700 | D7: 20000 | G7: Critical | J7: 50000 | M7: 6700 | P7: High Accumulated Payables
A8: 30/09/26 | B8: -70000 | D8: 20000 | G8: Critical | J8: 50000 | M8: 4300 | P8: No incoming cash, added expenses
A9: 46032 | B9: -81000 | D9: 20000 | G9: Critical | J9: 50000 | M9: 11000 | P9: increased operating expenses
A10: 46152 | B10: -85800 | D10: 20000 | G10: Critical | J10: 50000 | M10: 4800 | P10: Utilities and Supplier Dues
A11: 46305 | B11: -96300 | D11: 20000 | G11: Critical | J11: 50000 | M11: 10500 | P11: Cash outflow exceeds inflow
A12: 15/10/26 | B12: -103300 | D12: 20000 | G12: Critical | J12: 50000 | M12: 7000 | P12: No sales or major expenses
A13: 18/10/2026 | B13: -106500 | D13: 20000 | G13: Critical | J13: 50000 | M13: 3200 | P13: Severe cash deficit
A14: 20/10/26 | B14: -99000 | D14: 20000 | G14: Critical | J14: 50000 | M14: 7500 | P14: High Accumulated Liabilities
A15: n/a | B15: 0 | D15: N/A | G15: N/A | J15: N/A | M15: N/A | P15: N/A
A16: n/a | B16: 0 | D16: N/A | G16: N/A | J16: N/A | M16: N/A | P16: N/A

Sheet Dashboard
